zai_engine/__init__.py
zai_engine/ai_engine.py
zai_engine/connectivity.py
zai_engine/evaluator.py
zai_engine/game_engine.py
zai_engine/game_state.py
zai_engine/hex.py
zai_engine/move_generator.py
zai_engine/win_detector.py
zai_engine/entities/__init__.py
zai_engine/entities/move.py
zai_engine/entities/player.py
zai_engine-0.1.8.dist-info/METADATA
zai_engine-0.1.8.dist-info/WHEEL
zai_engine-0.1.8.dist-info/top_level.txt
zai_engine-0.1.8.dist-info/RECORD
