Metadata-Version: 2.4
Name: zai_engine
Version: 0.1.8
Summary: A robust game engine for the strategic board game Zai
Author-email: OVECJOE <vohachor@gmail.com>
License: MIT
Project-URL: Homepage, https://github.com/OVECJOE/zai
Project-URL: Repository, https://github.com/OVECJOE/zai
Keywords: game,strategy,hexagonal,board-game,ai
Classifier: Development Status :: 4 - Beta
Classifier: Intended Audience :: Developers
Classifier: License :: OSI Approved :: MIT License
Classifier: Programming Language :: Python :: 3
Classifier: Programming Language :: Python :: 3.8
Classifier: Programming Language :: Python :: 3.9
Classifier: Programming Language :: Python :: 3.10
Classifier: Programming Language :: Python :: 3.11
Requires-Python: >=3.10
Requires-Dist: pytest>=9.0.2
